kp_compression/__init__.py
kp_compression/myfunctions.py
kp_compression-0.2.6.dist-info/METADATA
kp_compression-0.2.6.dist-info/WHEEL
kp_compression-0.2.6.dist-info/top_level.txt
kp_compression-0.2.6.dist-info/RECORD
