Metadata-Version: 2.1
Name: kp-compression
Version: 0.2.6
Summary: Library to compress LSTM layers
Home-page: UNKNOWN
Author: Kolin Paul, Suyash Saxena and Varun Singh Negi
Author-email: UNKNOWN
License: IITD
Platform: UNKNOWN
Requires-Dist: numpy
Requires-Dist: torch
